[
    {
        "id": 1,
        "nombre": "Mochila Antirrobo",
        "precio": 50000,
        "description": "La Mochila Antirrobo es un modelo con apertura en la parte trasera que mantiene las pertenencias seguras.",
        "stock": 15,
        "deleted": false
    },
    {
        "id": 2,
        "nombre": "Matero Ecuador",
        "precio": 60000,
        "description": "Confeccionado en cordura cosida en efecto canelón, está envivado en sus bordes con pu a tono y forrado en silver (impermeable).",
        "stock": 15,
        "deleted": false
    },
    {
        "id": 3,
        "nombre": "Matero Armenia",
        "precio": 50000,
        "description": "El matero Armenia es un bolso tipo puffer confeccionado en sire canelón y forrado en silver.",
        "stock": 15,
        "deleted": false
    }
]